setup.cfg
setup.py
audiotrans/__init__.py
audiotrans/__main__.py
audiotrans/cli.py
audiotrans/core.py
audiotrans/load_transforms.py
audiotrans/transform.py
audiotrans/visualizer.py
audiotrans.egg-info/PKG-INFO
audiotrans.egg-info/SOURCES.txt
audiotrans.egg-info/dependency_links.txt
audiotrans.egg-info/entry_points.txt
audiotrans.egg-info/requires.txt
audiotrans.egg-info/top_level.txt
realtime_score_following/__init__.py
realtime_score_following/__main__.py
realtime_score_following/batch.py
realtime_score_following/core.py
realtime_score_following/tr/__init__.py
realtime_score_following/tr/following.py
realtime_score_following/tr/istft.py
realtime_score_following/tr/onset.py
realtime_score_following/tr/ssnmf.py
realtime_score_following/tr/stft.py
realtime_score_following/tr/string_to_int.py
realtime_score_following/utils/__init__.py
realtime_score_following/utils/istft.py
realtime_score_following/utils/parse_args.py
realtime_score_following/utils/parse_subargs.py
realtime_score_following/utils/stft.py
realtime_score_following/utils/string_to_int.py