Metadata-Version: 1.1
Name: audiotrans
Version: 0.1.0.dev0
Summary: Transform audio in real-time
Home-page: https://github.com/keik/audiotrans
Author: keik
Author-email: k4t0.kei@gmail.com
License: MIT
Platform: UNKNOWN
Classifier: License :: OSI Approved :: MIT License
Classifier: Intended Audience :: Developers
Classifier: Topic :: Multimedia :: Sound/Audio :: Conversion
Classifier: Programming Language :: Python
Classifier: Programming Language :: Python :: 3
Classifier: Programming Language :: Python :: 3.5
